NOTICE
coreason_identity/__init__.py
coreason_identity/config.py
coreason_identity/device_flow_client.py
coreason_identity/exceptions.py
coreason_identity/identity_mapper.py
coreason_identity/main.py
coreason_identity/manager.py
coreason_identity/models.py
coreason_identity/oidc_provider.py
coreason_identity/utils/__init__.py
coreason_identity/utils/logger.py
coreason_identity/validator.py
coreason_identity-0.2.0.dist-info/METADATA
coreason_identity-0.2.0.dist-info/WHEEL
coreason_identity-0.2.0.dist-info/licenses/LICENSE
coreason_identity-0.2.0.dist-info/licenses/NOTICE
coreason_identity-0.2.0.dist-info/RECORD
